MANIFEST.in
README.md
setup.py
lore/iris/__init__.py
lore/iris/api.py
lore/iris/objects.py
lore/iris/conf/__init__.py
lore/iris/conf/iris.yaml
lore_iris.egg-info/PKG-INFO
lore_iris.egg-info/SOURCES.txt
lore_iris.egg-info/dependency_links.txt
lore_iris.egg-info/entry_points.txt
lore_iris.egg-info/requires.txt
lore_iris.egg-info/top_level.txt