Metadata-Version: 2.1
Name: lore-iris
Version: 0.0.1b0
Summary: Programmatic access to thousands of public documents.
Home-page: https://api.iris.lore.ai
Author: Lore Ai
Author-email: iris@lore.ai
License: MIT
Platform: UNKNOWN
Classifier: License :: OSI Approved :: MIT License
Classifier: Programming Language :: Python :: 3
Classifier: Programming Language :: Python :: 3.7
